pynot/.extract_msg
pynot/.identify_msg
pynot/.instrument.cfg
pynot/.response_msg
pynot/VERSION
pynot/__init__.py
pynot/alfosc.py
pynot/calibs.py
pynot/efosc.py
pynot/extract_gui.py
pynot/extraction.py
pynot/fitsio.py
pynot/functions.py
pynot/identify_gui.py
pynot/images.py
pynot/insconfig.py
pynot/logging.py
pynot/main.py
pynot/operations.py
pynot/phot.py
pynot/phot_redux.py
pynot/redux.py
pynot/reports.py
pynot/response.py
pynot/response_gui.py
pynot/scired.py
pynot/scombine.py
pynot/skysub.py
pynot/tasks.py
pynot/transients.py
pynot/txtio.py
pynot/wavecal.py
pynot/wcs.py
pynot/welcome.py
pynot/calib/HeAr_linelist.dat
pynot/calib/HeNe_linelist.dat
pynot/calib/ThAr_linelist.dat
pynot/calib/al-gr18_pixeltable.dat
pynot/calib/al-gr19_pixeltable.dat
pynot/calib/al-gr4_pixeltable.dat
pynot/calib/al-gr7_pixeltable.dat
pynot/calib/alfosc_filters.dat
pynot/calib/default_options.yml
pynot/calib/default_options_img.yml
pynot/calib/ef-gr13_pixeltable.dat
pynot/calib/ef-gr14_pixeltable.dat
pynot/calib/ef-gr1_pixeltable.dat
pynot/calib/ef-gr3_pixeltable.dat
pynot/calib/efosc_filters.dat
pynot/calib/lapalma.ext
pynot/calib/lasilla.ext
pynot/calib/paranal.ext
pynot/calib/std/bd174708.dat
pynot/calib/std/bd262606.dat
pynot/calib/std/bd332642.dat
pynot/calib/std/bd75325.dat
pynot/calib/std/eg21.dat
pynot/calib/std/feige110.dat
pynot/calib/std/feige34.dat
pynot/calib/std/gd153.dat
pynot/calib/std/gd50.dat
pynot/calib/std/gd71.dat
pynot/calib/std/hd19445.dat
pynot/calib/std/hd84937.dat
pynot/calib/std/hd93521.dat
pynot/calib/std/he3.dat
pynot/calib/std/hiltner600.dat
pynot/calib/std/ltt3864.dat
pynot/calib/std/tcs_namelist.txt
pynot/calib/std/wolf1346.dat
pynot/data/__init__.py
pynot/data/alfosc.rules
pynot/data/efosc.rules
pynot/data/io.py
pynot/data/obs.py
pynot/data/organizer.py
pynot/data/help/welcome_msg_extract.html
pynot/data/help/welcome_msg_identify.html
pynot/data/help/welcome_msg_response.html
PyNOT_redux-2.1.2.dist-info/LICENSE
PyNOT_redux-2.1.2.dist-info/METADATA
PyNOT_redux-2.1.2.dist-info/WHEEL
PyNOT_redux-2.1.2.dist-info/entry_points.txt
PyNOT_redux-2.1.2.dist-info/top_level.txt
PyNOT_redux-2.1.2.dist-info/RECORD
