Metadata-Version: 2.1
Name: PyNOT-redux
Version: 2.1.2
Summary: Data Reduction Pipeline for NOT/ALFOSC
Home-page: https://github.com/jkrogager/PyNOT
Author: Jens-Kristian Krogager
Author-email: krogager.jk@gmail.com
License: MIT
Keywords: spectroscopy astronomy longslit data processing pipeline
Classifier: Development Status :: 4 - Beta
Classifier: Intended Audience :: Science/Research
Classifier: Topic :: Scientific/Engineering :: Astronomy
Classifier: License :: OSI Approved :: MIT License
Classifier: Programming Language :: Python :: 3
Requires-Python: >3.7
License-File: LICENSE
Requires-Dist: matplotlib
Requires-Dist: numpy
Requires-Dist: scipy
Requires-Dist: PyQt5
Requires-Dist: lmfit
Requires-Dist: astropy
Requires-Dist: astroscrappy
Requires-Dist: spectres
Requires-Dist: PyYAML
Requires-Dist: sep
Requires-Dist: astroalign
Requires-Dist: astroquery
Requires-Dist: beautifulsoup4
